setup.py
disqus/__init__.py
disqus/api.py
disqus/disqus_globals.py
disqus.egg-info/PKG-INFO
disqus.egg-info/SOURCES.txt
disqus.egg-info/dependency_links.txt
disqus.egg-info/entry_points.txt
disqus.egg-info/top_level.txt
disqus.egg-info/zip-safe