Metadata-Version: 1.0
Name: disqus
Version: 0.0.1
Summary: An API wrapper for Disqus (disqus.com)
Home-page: http://jarodl.com
Author: Jarod Luebbert
Author-email: jarod@disqus.com
License: MIT License
Keywords: disqus,API,commenting,community
Platform: UNKNOWN
Classifier: Development Status :: 3 - Alpha
Classifier: Environment :: Console
Classifier: Intended Audience :: Developers
Classifier: Natural Language :: English
Classifier: Operating System :: OS Independent
Classifier: Programming Language :: Python
Classifier: Topic :: Internet :: WWW/HTTP :: Dynamic Content :: CGI Tools/Libraries
Classifier: Topic :: Utilities
Classifier: License :: OSI Approved :: MIT License
